easyvllm/__init__.py
easyvllm/model_vllm.py
easyvllm/model_vllm_dev.py
easyvllm/util.py
easyvllm/cli/__init__.py
easyvllm/cli/cli.py
easyvllm/cli/decode.py
easyvllm/parsers/__init__.py
easyvllm/parsers/deepseek_r1_reasoning_parser.py
easyvllm/parsers/openthinker_reasoning_parser.py
easyvllm/parsers/simplescaling_reasoning_parser.py
easyvllm-0.1.0.dist-info/LICENSE
easyvllm-0.1.0.dist-info/METADATA
easyvllm-0.1.0.dist-info/WHEEL
easyvllm-0.1.0.dist-info/entry_points.txt
easyvllm-0.1.0.dist-info/top_level.txt
easyvllm-0.1.0.dist-info/RECORD
