Metadata-Version: 2.2
Name: easyvllm
Version: 0.1.0
Summary: Easy to use lightweight vllm tool with special support for Large Reasoning Model (LRM).
Home-page: https://github.com/XingYuSSS/easyvllm
Author: XingYuSSS
Author-email: hit-sxy@outlook.com
License: https://www.apache.org/licenses/LICENSE-2.0
Classifier: License :: OSI Approved :: MIT License
Classifier: Programming Language :: Python
Classifier: Programming Language :: Python :: 3
Classifier: Programming Language :: Python :: 3.10
Classifier: Programming Language :: Python :: 3.11
Classifier: Programming Language :: Python :: Implementation :: CPython
Classifier: Programming Language :: Python :: Implementation :: PyPy
Requires-Python: >=3.10.0
License-File: LICENSE
Requires-Dist: vllm>=0.7.3
Requires-Dist: fire
Requires-Dist: pandas
Requires-Dist: openai
Requires-Dist: ray[serve]
Dynamic: author
Dynamic: author-email
Dynamic: classifier
Dynamic: description
Dynamic: description-content-type
Dynamic: home-page
Dynamic: license
Dynamic: requires-dist
Dynamic: requires-python
Dynamic: summary
